fbrc/__init__.py
fbrc/frontend/build/asset-manifest.json
fbrc/frontend/build/index.html
fbrc/frontend/build/precache-manifest.0b57adb7c1e96ac694f60bf6d8ed57c3.js
fbrc/frontend/build/service-worker.js
fbrc/frontend/build/static/js/2.3d87aa55.chunk.js
fbrc/frontend/build/static/js/2.3d87aa55.chunk.js.LICENSE.txt
fbrc/frontend/build/static/js/2.3d87aa55.chunk.js.map
fbrc/frontend/build/static/js/main.f7702fa8.chunk.js
fbrc/frontend/build/static/js/main.f7702fa8.chunk.js.map
fbrc/frontend/build/static/js/runtime-main.44d30fc2.js
fbrc/frontend/build/static/js/runtime-main.44d30fc2.js.map
streamlit_firebase_remote_config_component-0.0.4.dist-info/LICENSE
streamlit_firebase_remote_config_component-0.0.4.dist-info/METADATA
streamlit_firebase_remote_config_component-0.0.4.dist-info/WHEEL
streamlit_firebase_remote_config_component-0.0.4.dist-info/top_level.txt
streamlit_firebase_remote_config_component-0.0.4.dist-info/RECORD
