Metadata-Version: 2.1
Name: streamlit-firebase-remote-config-component
Version: 0.0.4
Summary: Firebase Remote Config and Google Analytics for Streamlit
Home-page: 
Author: Granit Luzhnica
Author-email: granit.luzhnica@gmail.com
Requires-Python: >=3.1
License-File: LICENSE
Requires-Dist: streamlit (>=0.63)
